CHANGES.txt
buildout.cfg
setup.py
src/zc/__init__.py
src/zc.cacheheaders.egg-info/PKG-INFO
src/zc.cacheheaders.egg-info/SOURCES.txt
src/zc.cacheheaders.egg-info/dependency_links.txt
src/zc.cacheheaders.egg-info/namespace_packages.txt
src/zc.cacheheaders.egg-info/not-zip-safe
src/zc.cacheheaders.egg-info/requires.txt
src/zc.cacheheaders.egg-info/top_level.txt
src/zc/cacheheaders/README.txt
src/zc/cacheheaders/__init__.py
src/zc/cacheheaders/tests.py