Metadata-Version: 1.0
Name: zc.cacheheaders
Version: 1.4.0
Summary: Cache control utility functions
Home-page: UNKNOWN
Author: Aaron Lehmann
Author-email: aaron@zope.com
License: ZPL 2.1
Keywords: development build macro
Platform: UNKNOWN
Classifier: Framework :: Zope3
Classifier: Intended Audience :: Developers
Classifier: Topic :: Software Development :: Libraries :: Python Modules
